parkinson_detector_app/__init__.py
parkinson_detector_app/ai/dicom_processor.py
parkinson_detector_app/ai/ensemble_rules.py
parkinson_detector_app/ai/model_worker.py
parkinson_detector_app/common/__init__.py
parkinson_detector_app/common/const.py
parkinson_detector_app/common/files.py
parkinson_detector_app/common/settings.py
parkinson_detector_app/common/singleton.py
parkinson_detector_app/gui/__init__.py
parkinson_detector_app/gui/main_window.py
parkinson_detector_app/gui/resources/logo.ico
parkinson_detector_app/gui/widgets/about_widget.py
parkinson_detector_app/gui/widgets/dicom_preview_widget.py
parkinson_detector_app/gui/widgets/result_preview_widget.py
parkinson_detector_app/parkinson_detector_app.py
parkinson_detector_app/util/__init__.py
parkinson_detector_app/util/gdrive.py
parkinson_detector-0.0.1.dist-info/entry_points.txt
parkinson_detector-0.0.1.dist-info/LICENSE
parkinson_detector-0.0.1.dist-info/WHEEL
parkinson_detector-0.0.1.dist-info/METADATA
parkinson_detector-0.0.1.dist-info/RECORD
