Metadata-Version: 2.1
Name: parkinson-detector
Version: 0.0.1
Summary: An Ensemble of CNN Models for Parkinsons Disease Detection
Home-page: https://gitlab.com/digiratory/biomedimaging/parkinson-detector
License: GPL-3.0-only
Author: Aleksandr Sinitca
Author-email: amsinitca@etu.ru
Requires-Python: >=3.6,<4.0
Classifier: License :: OSI Approved :: GNU General Public License v3 (GPLv3)
Classifier: Programming Language :: Python :: 3
Classifier: Programming Language :: Python :: 3.6
Classifier: Programming Language :: Python :: 3.7
Classifier: Programming Language :: Python :: 3.8
Classifier: Topic :: Scientific/Engineering :: Artificial Intelligence
Classifier: Topic :: Scientific/Engineering :: Image Recognition
Classifier: Topic :: Scientific/Engineering :: Medical Science Apps.
Requires-Dist: PyQt5
Requires-Dist: appdirs
Requires-Dist: numpy (>=1.20.1,<2.0.0)
Requires-Dist: opencv-python
Requires-Dist: pillow
Requires-Dist: pydicom
Requires-Dist: pylibjpeg
Requires-Dist: pylibjpeg-libjpeg
Requires-Dist: pylibjpeg-openjpeg
Requires-Dist: requests
Requires-Dist: tensorflow (>=2.3.1,<3.0.0)
Project-URL: Repository, https://gitlab.com/digiratory/biomedimaging/parkinson-detector
